README.md
setup.cfg
setup.py
ajimoti_distributions/Binomialdistribution.py
ajimoti_distributions/Gaussiandistribution.py
ajimoti_distributions/Generaldistribution.py
ajimoti_distributions/__init__.py
ajimoti_distributions.egg-info/PKG-INFO
ajimoti_distributions.egg-info/SOURCES.txt
ajimoti_distributions.egg-info/dependency_links.txt
ajimoti_distributions.egg-info/not-zip-safe
ajimoti_distributions.egg-info/top_level.txt